timeir/__init__.py
timeir-0.0.3.dist-info/licenses/LICENCE.txt
timeir-0.0.3.dist-info/WHEEL
timeir-0.0.3.dist-info/METADATA
timeir-0.0.3.dist-info/RECORD
