Metadata-Version: 2.4
Name: timeir
Version: 0.0.3
Summary: python functions to extract and work with time.ir data
Author-email: 5j9 <5j9@users.noreply.github.com>
Requires-Python: >=3.12
License-File: LICENCE.txt
Requires-Dist: httpx
Project-URL: Homepage, https://github.com/5j9/timeir
